molecule_lib/__init__.py
molecule_lib/cif2pos.py
molecule_lib-2025.9.3.5.dist-info/licenses/LICENSE
molecule_lib-2025.9.3.5.dist-info/METADATA
molecule_lib-2025.9.3.5.dist-info/WHEEL
molecule_lib-2025.9.3.5.dist-info/top_level.txt
molecule_lib-2025.9.3.5.dist-info/RECORD
