Metadata-Version: 2.4
Name: molecule-lib
Version: 2025.9.3.5
Summary: A python library for manipulating molecular structures.
Author-email: Jeremy Neil Schroeder <jeremynschroeder@gmail.com>
License-Expression: GPL-3.0-or-later
Project-URL: Homepage, https://github.com/jerschro/molecule_lib
Project-URL: Documentation, https://jerschro.github.io/molecule_lib_documentation
Project-URL: Issues, https://github.com/jerschro/molecule_lib_documentation/issues
Classifier: Programming Language :: Python :: 3
Classifier: Operating System :: OS Independent
Requires-Python: >=3.10
License-File: LICENSE
Requires-Dist: numpy>=2.3.2
Provides-Extra: rdkit
Requires-Dist: rdkit; extra == "rdkit"
Dynamic: license-file
